{"cameraMode":{"drawMode":0,"name":"Shaded","section":"Shading Mode"},"sceneLighting":true,"audioPlay":false,"sceneViewState":{"showFog":true,"showMaterialUpdate":false,"showSkybox":true,"showFlares":true,"showImageEffects":true,"showParticleSystems":true},"in2DMode":false,"pivot":{"x":-32.8214225769043,"y":0.7198524475097656,"z":-8.962240219116211},"rotation":{"x":0.0050379023887217049,"y":0.7408061027526856,"z":-0.6716831922531128,"w":0.005556039046496153},"size":19.080703735351564,"orthographic":false}